slconf/__init__.py
slconf/slconf.py
nisystemlink_configuration-0.1.0.dist-info/LICENSE
nisystemlink_configuration-0.1.0.dist-info/METADATA
nisystemlink_configuration-0.1.0.dist-info/WHEEL
nisystemlink_configuration-0.1.0.dist-info/top_level.txt
nisystemlink_configuration-0.1.0.dist-info/RECORD
