Metadata-Version: 2.1
Name: nisystemlink-configuration
Version: 0.1.0
Summary: A command-line utility for managing SystemLink Server configurations
Home-page: https://github.com/ni/systemlink-configuration-utility
Author: NI
Maintainer: cameronwaterman
Maintainer-email: cameron.waterman@ni.com
License: MIT
Keywords: nisystemlink,systemlink
Platform: UNKNOWN
Classifier: Intended Audience :: Developers
Classifier: Intended Audience :: Manufacturing
Classifier: Intended Audience :: Science/Research
Classifier: Operating System :: Microsoft :: Windows
Classifier: Topic :: Software Development :: Libraries :: Python Modules
Classifier: Programming Language :: Python :: 3.7
Classifier: Programming Language :: Python :: 3.8
Classifier: License :: OSI Approved :: MIT License
Requires-Python: >=3.7
